booleanify.py
booleanify-0.1.1.dist-info/LICENSE
booleanify-0.1.1.dist-info/METADATA
booleanify-0.1.1.dist-info/WHEEL
booleanify-0.1.1.dist-info/RECORD
